CHANGES
LICENSE
MANIFEST.in
README.markdown
setup.py
demo/__init__.py
demo/imageserver_import.py
demo/imagestuff.py
demo/manage.py
demo/middleware.py
demo/settings.py
demo/urls.py
huImages.egg-info/SOURCES.txt
huimages/__init__.py
huimages/server.py
huimages.egg-info/PKG-INFO
huimages.egg-info/SOURCES.txt
huimages.egg-info/dependency_links.txt
huimages.egg-info/not-zip-safe
huimages.egg-info/requires.txt
huimages.egg-info/top_level.txt
huimages/imagebrowser/__init__.py
huimages/imagebrowser/forms.py
huimages/imagebrowser/models.py
huimages/imagebrowser/swfupload.swf
huimages/imagebrowser/urls.py
huimages/imagebrowser/views.py
huimages/imagebrowser/templates/imagebrowser/collection.html
huimages/imagebrowser/templates/imagebrowser/image.html
huimages/imagebrowser/templates/imagebrowser/startpage.html
huimages/imagebrowser/templates/imagebrowser/upload.html