Metadata-Version: 1.0
Name: huImages
Version: 2.2p3
Summary: Image storage & scaling in CouchDB.
Home-page: http://github.com/hudora/huImages/
Author: Maximillian Dornseif
Author-email: md@hudora.de
License: UNKNOWN
Platform: UNKNOWN
Classifier: License :: OSI Approved :: BSD License
Classifier: Intended Audience :: Developers
Classifier: Programming Language :: Python
